Metadata-Version: 2.1
Name: pyapplier
Version: 0.0.5b0
Summary: .scrobbler.log (Rockbox offline last.fm scrobling format) submiter
Home-page: https://github.com/ultraelephant/pyapplier
Author: Aleksey Kurnosov
Author-email: akkurnosov@gmail.com
License: UNKNOWN
Platform: UNKNOWN
Classifier: Programming Language :: Python :: 3
Classifier: Operating System :: POSIX :: Linux
